Metadata-Version: 1.0
Name: gaubin-distributions
Version: 0.1
Summary: Gaussian and Binomial distributions
Home-page: UNKNOWN
Author: Shivansh Aggarwal
Author-email: UNKNOWN
License: UNKNOWN
Platform: UNKNOWN
